hello/__init__.py
hello/hello.py
sayhellotosaurabh-0.0.1.dist-info/LICENSE
sayhellotosaurabh-0.0.1.dist-info/METADATA
sayhellotosaurabh-0.0.1.dist-info/WHEEL
sayhellotosaurabh-0.0.1.dist-info/top_level.txt
sayhellotosaurabh-0.0.1.dist-info/RECORD
